autoengineer_cli/__init__.py
autoengineer_cli/agents.py
autoengineer_cli/config.py
autoengineer_cli/main.py
autoengineer_cli/tools/__init__.py
autoengineer_cli/tools/file_writer.py
autoengineer_cli/tools/podman_sandbox.py
autoengineer_cli-0.1.0.dist-info/METADATA
autoengineer_cli-0.1.0.dist-info/WHEEL
autoengineer_cli-0.1.0.dist-info/entry_points.txt
autoengineer_cli-0.1.0.dist-info/licenses/LICENSE
autoengineer_cli-0.1.0.dist-info/RECORD
