Metadata-Version: 2.4
Name: autoengineer-cli
Version: 0.1.0
Summary: Autonomous Software Engineering Multi-Agent System using AI agents to analyze, implement, test, and review code
Project-URL: Homepage, https://github.com/autoengineer/autoengineer-cli
Project-URL: Documentation, https://github.com/autoengineer/autoengineer-cli#readme
Project-URL: Repository, https://github.com/autoengineer/autoengineer-cli
Project-URL: Issues, https://github.com/autoengineer/autoengineer-cli/issues
Author: AutoEngineer Team
License-Expression: MIT
License-File: LICENSE
Keywords: agents,ai,autonomous,code-generation,code-review,crewai,llm,multi-agent,software-engineering
Classifier: Development Status :: 4 - Beta
Classifier: Environment :: Console
Classifier: Intended Audience :: Developers
Classifier: License :: OSI Approved :: MIT License
Classifier: Operating System :: OS Independent
Classifier: Programming Language :: Python :: 3
Classifier: Programming Language :: Python :: 3.10
Classifier: Programming Language :: Python :: 3.11
Classifier: Programming Language :: Python :: 3.12
Classifier: Topic :: Scientific/Engineering :: Artificial Intelligence
Classifier: Topic :: Software Development :: Code Generators
Requires-Python: >=3.10
Requires-Dist: click>=8.1.0
Requires-Dist: crewai>=0.28.0
Requires-Dist: fastapi>=0.100.0
Requires-Dist: litellm>=1.30.0
Requires-Dist: podman>=5.0.0
Requires-Dist: pydantic>=2.0.0
Requires-Dist: python-dotenv>=1.0.0
Provides-Extra: dev
Requires-Dist: black>=23.0.0; extra == 'dev'
Requires-Dist: pytest-cov>=4.0.0; extra == 'dev'
Requires-Dist: pytest>=7.0.0; extra == 'dev'
Requires-Dist: ruff>=0.1.0; extra == 'dev'
